{
	"id": "ed0d376f-4430-4c23-a79b-a55165ea0fda",
	"name": "ServeRest",
	"values": [
		{
			"key": "baseUrl",
			"value": "https://serverest.dev/",
			"type": "default",
			"enabled": true
		},
		{
			"key": "accessToken",
			"value": "",
			"type": "any",
			"enabled": true
		},
		{
			"key": "randomProduct",
			"value": "",
			"type": "any",
			"enabled": true
		},
		{
			"key": "resJson",
			"value": "",
			"type": "any",
			"enabled": true
		},
		{
			"key": "newProductId",
			"value": "",
			"type": "any",
			"enabled": true
		}
	],
	"_postman_variable_scope": "environment",
	"_postman_exported_at": "2024-10-09T22:25:30.451Z",
	"_postman_exported_using": "Postman/11.15.0"
}